keyt/__init__.py
keyt/__main__.py
keyt/cli.py
keyt-1.2.0.dist-info/LICENSE
keyt-1.2.0.dist-info/METADATA
keyt-1.2.0.dist-info/WHEEL
keyt-1.2.0.dist-info/entry_points.txt
keyt-1.2.0.dist-info/top_level.txt
keyt-1.2.0.dist-info/RECORD
