Metadata-Version: 2.1
Name: keyt
Version: 1.2.0
Summary: Stateless password manager and generator.
Home-page: https://github.com/deoktr/keyt
Author: keyt
Author-email: 
License: MIT license
Project-URL: Bug Tracker, https://github.com/deoktr/keyt/issues
Classifier: Development Status :: 5 - Production/Stable
Classifier: Intended Audience :: End Users/Desktop
Classifier: License :: OSI Approved :: MIT License
Classifier: Natural Language :: English
Classifier: Programming Language :: Python :: 3
Classifier: Programming Language :: Python :: 3.5
Classifier: Programming Language :: Python :: 3.6
Classifier: Programming Language :: Python :: 3.7
Classifier: Programming Language :: Python :: 3.8
Classifier: Programming Language :: Python :: 3.9
Classifier: Programming Language :: Python :: 3.10
Classifier: Programming Language :: Python :: 3.11
Classifier: Topic :: Security
Requires-Python: >=3.5
License-File: LICENSE
Requires-Dist: pyperclip
Requires-Dist: base58
